pyhtmlgen/__init__.py
pyhtmlgen/generators.py
pyhtmlgen-0.0.2.dist-info/LICENSE
pyhtmlgen-0.0.2.dist-info/METADATA
pyhtmlgen-0.0.2.dist-info/WHEEL
pyhtmlgen-0.0.2.dist-info/top_level.txt
pyhtmlgen-0.0.2.dist-info/RECORD
