Metadata-Version: 2.1
Name: pyhtmlgen
Version: 0.0.2
Summary: small package to easily write html code within a python script
Home-page: https://github.com/danvran/pyhtmlgen
Author: danvran
Author-email: vranjes@hsu-hh.de
License: UNKNOWN
Project-URL: Bug Tracker, https://github.com/danvran/pyhtmlgen/issues
Platform: UNKNOWN
Classifier: Programming Language :: Python :: 3
Classifier: License :: OSI Approved :: MIT License
Classifier: Operating System :: OS Independent
Requires-Python: >=3.6
License-File: LICENSE
